knd/__init__.py
knd/ai.py
knd/api.py
knd/mem_functions.py
knd/mem_models.py
knd/memory.py
knd/prompts.py
knd/py.typed
knd/tools.py
knd/utils.py
knd-0.1.4.dist-info/METADATA
knd-0.1.4.dist-info/WHEEL
knd-0.1.4.dist-info/RECORD
